{
  "kind": "feature_evidence_report",
  "features": [
    {
      "featureId": "feature-update-the-chapter-verses-table-read-gita-chapters-chapter-detail-to-remove-the-hindi-translation-column-while-retaining-the-gen-z-interpretation-column",
      "featureTitle": "Update the Chapter verses table (Read Gita → Chapters → Chapter detail) to remove the Hindi translation column while retaining the Gen Z interpretation column.",
      "files": [
        "frontend/src/pages/ReadGita/ChapterDetailView.tsx"
      ],
      "components": [
        "core-infrastructure@1.0.2",
        "shadcn-ui@1.0.0",
        "build-template-react@1.0.0",
        "initial-app@1.0.0",
        "github-export-icp-cli@1.0.0"
      ],
      "testIds": [
        "REQ-1"
      ],
      "confidence": "high"
    },
    {
      "featureId": "feature-remove-hindi-translation-from-the-single-verse-detail-ui-while-keeping-the-gen-z-interpretation-section-intact",
      "featureTitle": "Remove Hindi translation from the single-verse detail UI while keeping the Gen Z interpretation section intact.",
      "files": [
        "frontend/src/components/verse/VerseCard.tsx"
      ],
      "components": [
        "core-infrastructure@1.0.2",
        "shadcn-ui@1.0.0",
        "build-template-react@1.0.0",
        "initial-app@1.0.0",
        "github-export-icp-cli@1.0.0"
      ],
      "testIds": [
        "REQ-2"
      ],
      "confidence": "high"
    }
  ]
}